xps_crypto/alembic.ini
xps_crypto/api/__init__.py
xps_crypto/api/errors/__init__.py
xps_crypto/api/errors/base.py
xps_crypto/api/errors/general.py
xps_crypto/api/errors/handlers.py
xps_crypto/api/middlewares/__init__.py
xps_crypto/api/middlewares/cors_middleware.py
xps_crypto/api/middlewares/exceptions_middleware.py
xps_crypto/api/urls.py
xps_crypto/api/wallets/__init__.py
xps_crypto/api/wallets/serializers.py
xps_crypto/api/wallets/views.py
xps_crypto/asgi.py
xps_crypto/config.py
xps_crypto/database.py
xps_crypto/incoming_request_log/__init__.py
xps_crypto/incoming_request_log/context.py
xps_crypto/incoming_request_log/middleware.py
xps_crypto/incoming_request_log/model_mixin.py
xps_crypto/incoming_request_log/request_enrichment.py
xps_crypto/migrations/README
xps_crypto/migrations/env.py
xps_crypto/migrations/script.py.mako
xps_crypto-0.1.0.dist-info/WHEEL
xps_crypto-0.1.0.dist-info/METADATA
xps_crypto-0.1.0.dist-info/RECORD
